centrex_tlf-0.1.8.4.dist-info/METADATA
centrex_tlf-0.1.8.4.dist-info/WHEEL
centrex_tlf-0.1.8.4.dist-info/licenses/LICENSE
centrex_tlf/__init__.py
centrex_tlf/centrex_tlf_rust.cp310-win_amd64.pyd
centrex_tlf/centrex_tlf_rust.pyi
centrex_tlf/constants/__init__.py
centrex_tlf/constants/constants.py
centrex_tlf/constants/py.typed
centrex_tlf/couplings/__init__.py
centrex_tlf/couplings/branching.py
centrex_tlf/couplings/collapse.py
centrex_tlf/couplings/coupling_matrix.py
centrex_tlf/couplings/polarization.py
centrex_tlf/couplings/py.typed
centrex_tlf/couplings/transition.py
centrex_tlf/couplings/utils.py
centrex_tlf/couplings/utils_compact.py
centrex_tlf/hamiltonian/B_coupled.py
centrex_tlf/hamiltonian/B_coupled_Omega/__init__.py
centrex_tlf/hamiltonian/B_coupled_Omega/ld.py
centrex_tlf/hamiltonian/B_coupled_Omega/mhf.py
centrex_tlf/hamiltonian/B_coupled_Omega/nsr.py
centrex_tlf/hamiltonian/B_coupled_Omega/rotational.py
centrex_tlf/hamiltonian/B_coupled_Omega/stark.py
centrex_tlf/hamiltonian/B_coupled_Omega/zeeman.py
centrex_tlf/hamiltonian/B_uncoupled.py
centrex_tlf/hamiltonian/X_uncoupled.py
centrex_tlf/hamiltonian/__init__.py
centrex_tlf/hamiltonian/basis_transformations.py
centrex_tlf/hamiltonian/constants.py
centrex_tlf/hamiltonian/dark_bright.py
centrex_tlf/hamiltonian/general_uncoupled.py
centrex_tlf/hamiltonian/generate_hamiltonian.py
centrex_tlf/hamiltonian/matrix_elements_electric_dipole.py
centrex_tlf/hamiltonian/matrix_elements_electric_quadrupole.py
centrex_tlf/hamiltonian/py.typed
centrex_tlf/hamiltonian/quantum_operators.py
centrex_tlf/hamiltonian/reduced_hamiltonian.py
centrex_tlf/hamiltonian/utils.py
centrex_tlf/hamiltonian/wigner.py
centrex_tlf/lindblad/__init__.py
centrex_tlf/lindblad/generate_hamiltonian.py
centrex_tlf/lindblad/generate_system_of_equations.py
centrex_tlf/lindblad/py.typed
centrex_tlf/lindblad/utils.py
centrex_tlf/lindblad/utils_compact.py
centrex_tlf/lindblad/utils_decay.py
centrex_tlf/lindblad/utils_setup.py
centrex_tlf/py.typed
centrex_tlf/states/__init__.py
centrex_tlf/states/find_states.py
centrex_tlf/states/generate_states.py
centrex_tlf-0.1.8.4.dist-info/RECORD
