Metadata-Version: 2.4
Name: centrex-tlf
Version: 0.1.8.4
Requires-Dist: numpy>=2
Requires-Dist: scipy>=1.13
Requires-Dist: sympy>=1.13.2
Requires-Dist: pandas>=2
Requires-Dist: typing-extensions>=4.12.2
Requires-Dist: matplotlib>=3.10.8
Requires-Dist: pytest>=7.1.2 ; extra == 'dev'
Requires-Dist: mypy>=0.961 ; extra == 'dev'
Requires-Dist: ruff ; extra == 'dev'
Provides-Extra: dev
License-File: LICENSE
Summary: 
Author-email: ograsdijk <o.grasdijk@gmail.com>
License: MIT
Requires-Python: >=3.10
Project-URL: Repository, https://github.com/ograsdijk/CeNTREX-TlF
